[{"order": 1.0, "name": "Otev\u00edrac\u00ed doba parku P.Bezru\u010de", "question": "Chcete aby byl park P. Bezru\u010de ve\u0159ejn\u011b p\u0159\u00edstupn\u00fd i po 22 hodin\u011b?", "id": "1", "description": ""}, {"order": 2.0, "name": "Rafinersk\u00fd les\u00edk", "question": "Chcete, aby byl z Rafin\u00e9rsk\u00e9ho les\u00edka znovu les a sou\u010dasn\u00e9 z\u00e1bavn\u00ed atrakce byly p\u0159esunuty na vhodn\u011bj\u0161\u00ed m\u00edsto?", "id": "2", "description": ""}, {"order": 3.0, "name": "Lesopark Na Pansk\u00e9m", "question": "Chcete, aby v lokalit\u011b \"Na Pansk\u00e9m\" vznikl regul\u00e9rn\u00ed les pro zv\u011b\u0159 m\u00edsto pl\u00e1novan\u00e9ho volno\u010dasov\u00e9ho lesoparku pro lidi?", "id": "3", "description": ""}, {"order": 4.0, "name": "Meandry \u0159eky Odry", "question": "M\u011blo by se m\u011bsto zasadit o v\u011bt\u0161\u00ed ochranu Meandr\u016f \u0159eky Odry a roz\u0161\u00ed\u0159en\u00ed chr\u00e1n\u011bn\u00e9 z\u00f3ny ?", "id": "4", "description": ""}, {"order": 5.0, "name": "Aleje a stromo\u0159ad\u00ed", "question": "Jste pro obnovu alej\u00ed a stromo\u0159ad\u00ed ve m\u011bst\u011b?", "id": "5", "description": ""}, {"order": 6.0, "name": "Sv\u011bteln\u00e9 zne\u010di\u0161t\u011bn\u00ed", "question": "M\u011blo by se investovat do pouli\u010dn\u00edho osv\u011btlen\u00ed neprodukuj\u00edc\u00edho sv\u011bteln\u00e9 zne\u010di\u0161t\u011bn\u00ed i za cenu vy\u0161\u0161\u00edch po\u0159izovac\u00edch n\u00e1klad\u016f?", "id": "6", "description": ""}, {"order": 7.0, "name": "Anto\u0161ovice", "question": "M\u011bl by se vy\u010distit M\u017eikov v Anto\u0161ovic\u00edch?", "id": "7", "description": ""}, {"order": 8.0, "name": "\u00datulek pro psy", "question": "M\u011bl by se modernizovat \u00fatulek pro psy ?", "id": "8", "description": ""}, {"order": 9.0, "name": "Recykla\u010dn\u00ed ta\u0161ky", "question": "Chcete, aby m\u011bstsk\u00fd podnik BM servis a.s. distribuoval ta\u0161ky na recyklaci stejn\u011b jako OZO v Ostrav\u011b ?", "id": "9", "description": ""}, {"order": 10.0, "name": "N\u00e1doby na odpad", "question": "Chcete, aby se ve m\u011bst\u011b vym\u011bnily recykla\u010dn\u00ed n\u00e1doby za n\u00e1doby s odsouvateln\u00fdm vrchem jako maj\u00ed v Ostrav\u011b nebo jako b\u011b\u017en\u011b pou\u017e\u00edv\u00e1me na sm\u011bsn\u00fd odpad?", "id": "10", "description": ""}, {"order": 11.0, "name": "Poplatky za odpad", "question": "Chcete, aby m\u011bsto odpustilo poplatky za odpad t\u011bm dom\u016fm, kter\u00e9 sn\u00ed\u017e\u00ed sv\u016fj sm\u011bsn\u00fd odpad na minimum?", "id": "11", "description": ""}, {"order": 12.0, "name": "Cyklodoprava", "question": "Chcete, aby m\u011bsto v\u00fdrazn\u011bji podpo\u0159ilo cyklodopravu ?", "id": "12", "description": ""}, {"order": 13.0, "name": "Vlast\u00ed MHD", "question": "Chcete, aby m\u011blo m\u011bsto svou vlastn\u00ed m\u011bstskou hromadnou dopravu a investovalo do n\u00e1kup\u016f autobus\u016f \u010di jin\u00fdch dopravn\u00edch prost\u0159edk\u016f ?", "id": "13", "description": ""}, {"order": 14.0, "name": "Senior taxi", "question": "M\u00e1 se nad\u00e1le zachovat slu\u017eba Taxi pro seniory?", "id": "14", "description": ""}, {"order": 15.0, "name": "Tramvaje", "question": "M\u00e1 se ve m\u011bst\u011b obnovit tramvajov\u00e1 doprava s mo\u017enost\u00ed napojit se na s\u00ed\u0165 v Ostrav\u011b ?", "id": "15", "description": "Tramvajov\u00e1 doprava existovala v Bohum\u00edn\u011b v letech 1902 a\u017e 1973"}, {"order": 16.0, "name": "Nadzemn\u00ed parkovi\u0161t\u011b", "question": "Chcete aby ve m\u011bst\u011b byly postaveny nadzemn\u00ed \u010di podzemn\u00ed gar\u00e1\u017ee ?", "id": "16", "description": ""}, {"order": 17.0, "name": "N\u00e1kupn\u00ed st\u0159edisko", "question": "Jste pro, aby v prostoru okol\u00ed Kauflandu vyrostlo dal\u0161\u00ed n\u00e1kupn\u00ed st\u0159edisko?", "id": "17", "description": "(za Rafinersk\u00fdm les\u00edkem)"}, {"order": 18.0, "name": "Ve\u0159ejn\u011b prosp\u011b\u0161n\u00ed pracovn\u00edci", "question": "Souhlas\u00edte s nav\u00fd\u0161en\u00edm po\u010dtu ve\u0159ejn\u011b prosp\u011b\u0161n\u00fdch pracovn\u00edk\u016f?", "id": "18", "description": ""}, {"order": 19.0, "name": "Bezdomovci na n\u00e1dra\u017e\u00ed", "question": "Jste pro zachov\u00e1n\u00ed denn\u00ed m\u00edstnosti pro bezdomovce na n\u00e1dra\u017e\u00ed?", "id": "19", "description": ""}, {"order": 20.0, "name": "Odkup ubytoven", "question": "Jste pro to, aby m\u011bsto odkoupilo ubytovnu na n\u00e1m\u011bst\u00ed i za cenu, kter\u00e1 n\u011bkolikan\u00e1sobn\u011b p\u0159evy\u0161uje tr\u017en\u00ed?", "id": "20", "description": ""}, {"order": 21.0, "name": "M\u011bstsk\u00e1 polcie", "question": "M\u011bl by se pos\u00edlit sbor m\u011bstsk\u00e9 policie ?", "id": "21", "description": ""}, {"order": 22.0, "name": "Rom\u0161t\u00ed asistenti", "question": "M\u011bla by m\u011bstsk\u00e1 policie zam\u011bstnat romsk\u00e9 asistenty, kte\u0159\u00ed by chodili do probl\u00e9mov\u00fdch lokalit se str\u00e1\u017en\u00edky a s mo\u017enost\u00ed, \u017ee se \u010dasem sami stanou str\u00e1\u017en\u00edky?", "id": "22", "description": ""}, {"order": 23.0, "name": "Kamery", "question": "Jste pro, aby ve m\u011bst\u011b byly instalov\u00e1ny dal\u0161\u00ed kamery ?", "id": "23", "description": ""}, {"order": 24.0, "name": "V\u00fdkup kov\u016f", "question": "Jste pro z\u00e1kaz v\u00fdkup\u016f drah\u00fdch kov\u016f od nepodnikatel\u016f v komer\u010dn\u00edch sb\u011brn\u00e1ch surovin?", "id": "24", "description": "tento krok by m\u011bl zabr\u00e1nit st\u00e1le \u010dast\u011bj\u0161\u00edm kr\u00e1de\u017e\u00edm a n\u00e1jezd\u016fm hlavn\u011b na domka\u0159e, z\u00e1rove\u0148 jde o z\u00e1sah do voln\u00e9ho podnik\u00e1n\u00ed"}, {"order": 25.0, "name": "V\u00fdkup kov\u016f II", "question": "Jste pro to, aby ob\u010dan\u00e9 museli odevzd\u00e1vat kovov\u00fd odpad pouze do m\u011bstsk\u00e9 sb\u011brny a to bez odm\u011bny?", "id": "25", "description": ""}, {"order": 26.0, "name": "SDH Kopytov", "question": "M\u011bla by p\u0159i SDH (sbor dobrovoln\u00fdch hasi\u010d\u016f) Kopytov znovu vzniknout JPO (jednotka po\u017e\u00e1rn\u00ed ochrany)", "id": "26", "description": ""}, {"order": 27.0, "name": "Pam\u00e1tn\u00edk padl\u00fdm ve Star\u00e9m Bohum\u00edn\u011b", "question": "M\u011bl by se pam\u00e1tn\u00edk padl\u00fdm na n\u00e1m\u011bst\u00ed ve Star\u00e9m Bohum\u00edn\u011b p\u0159esunout na h\u0159bitov?", "id": "27", "description": ""}, {"order": 28.0, "name": "Centrum pro podnikatele a \u0159emesln\u00edky", "question": "M\u011blo by ve m\u011bst\u011b vzniknout centrum pro za\u010d\u00ednaj\u00edc\u00ed podnikatele a \u0159emesln\u00edky ?", "id": "28", "description": ""}, {"order": 29.0, "name": "Smlouvy na internetu", "question": "M\u011bsto by m\u011blo zve\u0159ej\u0148ovat v\u0161echny sv\u00e9 smlouvy na internetu.", "id": "29", "description": ""}]