[{"question": 9, "votes": -1, "voter": 39}, {"question": 18, "votes": 1, "voter": 39}, {"question": 13, "votes": 1, "voter": 39}, {"question": 39, "votes": -1, "voter": 39}, {"question": 26, "votes": -1, "voter": 39}, {"question": 23, "votes": -1, "voter": 39}, {"question": 33, "votes": -1, "voter": 39}, {"question": 6, "votes": 1, "voter": 39}, {"question": 37, "votes": -1, "voter": 39}, {"question": 5, "votes": 1, "voter": 39}, {"question": 35, "votes": 1, "voter": 39}, {"question": 17, "votes": 1, "voter": 39}, {"question": 3, "votes": 1, "voter": 39}, {"question": 15, "votes": 1, "voter": 39}, {"question": 20, "votes": 0, "voter": 39}, {"question": 24, "votes": -1, "voter": 39}, {"question": 21, "votes": 0, "voter": 39}, {"question": 31, "votes": 1, "voter": 39}, {"question": 27, "votes": -1, "voter": 39}, {"question": 16, "votes": 1, "voter": 39}, {"question": 11, "votes": 1, "voter": 39}, {"question": 25, "votes": 1, "voter": 39}, {"question": 8, "votes": 1, "voter": 39}, {"question": 2, "votes": 0, "voter": 39}, {"question": 22, "votes": 1, "voter": 39}, {"question": 7, "votes": 1, "voter": 39}, {"question": 1, "votes": -1, "voter": 39}, {"question": 12, "votes": 1, "voter": 39}, {"question": 10, "votes": 1, "voter": 39}, {"question": 14, "votes": 1, "voter": 39}, {"question": 19, "votes": 1, "voter": 39}, {"question": 34, "votes": -1, "voter": 39}, {"question": 36, "votes": 0, "voter": 39}, {"question": 38, "votes": 0, "voter": 39}, {"question": 32, "votes": 1, "voter": 39}, {"question": 9, "votes": -1, "voter": 40}, {"question": 18, "votes": 1, "voter": 40}, {"question": 13, "votes": 1, "voter": 40}, {"question": 39, "votes": -1, "voter": 40}, {"question": 26, "votes": 0, "voter": 40}, {"question": 23, "votes": 1, "voter": 40}, {"question": 33, "votes": 0, "voter": 40}, {"question": 6, "votes": 1, "voter": 40}, {"question": 37, "votes": 0, "voter": 40}, {"question": 5, "votes": 1, "voter": 40}, {"question": 35, "votes": 1, "voter": 40}, {"question": 17, "votes": 0, "voter": 40}, {"question": 3, "votes": 1, "voter": 40}, {"question": 15, "votes": 0, "voter": 40}, {"question": 20, "votes": 1, "voter": 40}, {"question": 24, "votes": -1, "voter": 40}, {"question": 21, "votes": 1, "voter": 40}, {"question": 31, "votes": 1, "voter": 40}, {"question": 27, "votes": -1, "voter": 40}, {"question": 16, "votes": 0, "voter": 40}, {"question": 11, "votes": 1, "voter": 40}, {"question": 25, "votes": 1, "voter": 40}, {"question": 8, "votes": 1, "voter": 40}, {"question": 2, "votes": 0, "voter": 40}, {"question": 22, "votes": 1, "voter": 40}, {"question": 7, "votes": 1, "voter": 40}, {"question": 1, "votes": 1, "voter": 40}, {"question": 12, "votes": 0, "voter": 40}, {"question": 10, "votes": -1, "voter": 40}, {"question": 14, "votes": 1, "voter": 40}, {"question": 19, "votes": 1, "voter": 40}, {"question": 34, "votes": -1, "voter": 40}, {"question": 36, "votes": 1, "voter": 40}, {"question": 38, "votes": 1, "voter": 40}, {"question": 32, "votes": 0, "voter": 40}, {"question": 9, "votes": -1, "voter": 41}, {"question": 18, "votes": 1, "voter": 41}, {"question": 13, "votes": 1, "voter": 41}, {"question": 39, "votes": -1, "voter": 41}, {"question": 26, "votes": 1, "voter": 41}, {"question": 23, "votes": 1, "voter": 41}, {"question": 33, "votes": -1, "voter": 41}, {"question": 6, "votes": 1, "voter": 41}, {"question": 37, "votes": 0, "voter": 41}, {"question": 5, "votes": 1, "voter": 41}, {"question": 35, "votes": -1, "voter": 41}, {"question": 17, "votes": 1, "voter": 41}, {"question": 3, "votes": 0, "voter": 41}, {"question": 15, "votes": 1, "voter": 41}, {"question": 20, "votes": 1, "voter": 41}, {"question": 24, "votes": 1, "voter": 41}, {"question": 21, "votes": -1, "voter": 41}, {"question": 31, "votes": 1, "voter": 41}, {"question": 27, "votes": -1, "voter": 41}, {"question": 16, "votes": -1, "voter": 41}, {"question": 11, "votes": 1, "voter": 41}, {"question": 25, "votes": 1, "voter": 41}, {"question": 8, "votes": 1, "voter": 41}, {"question": 2, "votes": 0, "voter": 41}, {"question": 22, "votes": 1, "voter": 41}, {"question": 7, "votes": 1, "voter": 41}, {"question": 1, "votes": -1, "voter": 41}, {"question": 12, "votes": 1, "voter": 41}, {"question": 10, "votes": 1, "voter": 41}, {"question": 14, "votes": 1, "voter": 41}, {"question": 19, "votes": 1, "voter": 41}, {"question": 34, "votes": 1, "voter": 41}, {"question": 36, "votes": 1, "voter": 41}, {"question": 38, "votes": 0, "voter": 41}, {"question": 32, "votes": 0, "voter": 41}, {"question": 9, "votes": 1, "voter": 47}, {"question": 18, "votes": -1, "voter": 47}, {"question": 13, "votes": 1, "voter": 47}, {"question": 39, "votes": -1, "voter": 47}, {"question": 26, "votes": 1, "voter": 47}, {"question": 23, "votes": -1, "voter": 47}, {"question": 33, "votes": -1, "voter": 47}, {"question": 6, "votes": -1, "voter": 47}, {"question": 37, "votes": 0, "voter": 47}, {"question": 5, "votes": -1, "voter": 47}, {"question": 35, "votes": -1, "voter": 47}, {"question": 17, "votes": 1, "voter": 47}, {"question": 3, "votes": 0, "voter": 47}, {"question": 15, "votes": -1, "voter": 47}, {"question": 20, "votes": -1, "voter": 47}, {"question": 24, "votes": -1, "voter": 47}, {"question": 21, "votes": 0, "voter": 47}, {"question": 31, "votes": 1, "voter": 47}, {"question": 27, "votes": -1, "voter": 47}, {"question": 16, "votes": -1, "voter": 47}, {"question": 11, "votes": 1, "voter": 47}, {"question": 25, "votes": 1, "voter": 47}, {"question": 8, "votes": -1, "voter": 47}, {"question": 2, "votes": 1, "voter": 47}, {"question": 22, "votes": -1, "voter": 47}, {"question": 7, "votes": 1, "voter": 47}, {"question": 1, "votes": -1, "voter": 47}, {"question": 12, "votes": 1, "voter": 47}, {"question": 10, "votes": -1, "voter": 47}, {"question": 14, "votes": 1, "voter": 47}, {"question": 19, "votes": 0, "voter": 47}, {"question": 34, "votes": 1, "voter": 47}, {"question": 36, "votes": 1, "voter": 47}, {"question": 38, "votes": -1, "voter": 47}, {"question": 32, "votes": 0, "voter": 47}, {"question": 9, "votes": -1, "voter": 48}, {"question": 18, "votes": -1, "voter": 48}, {"question": 13, "votes": 1, "voter": 48}, {"question": 39, "votes": -1, "voter": 48}, {"question": 26, "votes": 1, "voter": 48}, {"question": 23, "votes": 1, "voter": 48}, {"question": 33, "votes": 1, "voter": 48}, {"question": 6, "votes": 1, "voter": 48}, {"question": 37, "votes": -1, "voter": 48}, {"question": 5, "votes": 1, "voter": 48}, {"question": 35, "votes": 1, "voter": 48}, {"question": 17, "votes": 1, "voter": 48}, {"question": 3, "votes": -1, "voter": 48}, {"question": 15, "votes": 1, "voter": 48}, {"question": 20, "votes": 1, "voter": 48}, {"question": 24, "votes": -1, "voter": 48}, {"question": 21, "votes": -1, "voter": 48}, {"question": 31, "votes": 1, "voter": 48}, {"question": 27, "votes": -1, "voter": 48}, {"question": 16, "votes": 1, "voter": 48}, {"question": 11, "votes": 1, "voter": 48}, {"question": 25, "votes": 1, "voter": 48}, {"question": 8, "votes": 1, "voter": 48}, {"question": 2, "votes": -1, "voter": 48}, {"question": 22, "votes": 1, "voter": 48}, {"question": 7, "votes": 1, "voter": 48}, {"question": 1, "votes": 1, "voter": 48}, {"question": 12, "votes": 1, "voter": 48}, {"question": 10, "votes": -1, "voter": 48}, {"question": 14, "votes": 1, "voter": 48}, {"question": 19, "votes": 1, "voter": 48}, {"question": 34, "votes": -1, "voter": 48}, {"question": 36, "votes": 1, "voter": 48}, {"question": 38, "votes": 1, "voter": 48}, {"question": 32, "votes": -1, "voter": 48}, {"question": 9, "votes": -1, "voter": 43}, {"question": 18, "votes": -1, "voter": 43}, {"question": 13, "votes": 1, "voter": 43}, {"question": 39, "votes": -1, "voter": 43}, {"question": 26, "votes": 1, "voter": 43}, {"question": 23, "votes": 1, "voter": 43}, {"question": 33, "votes": -1, "voter": 43}, {"question": 6, "votes": 1, "voter": 43}, {"question": 37, "votes": 1, "voter": 43}, {"question": 5, "votes": 1, "voter": 43}, {"question": 35, "votes": -1, "voter": 43}, {"question": 17, "votes": 1, "voter": 43}, {"question": 3, "votes": -1, "voter": 43}, {"question": 15, "votes": 1, "voter": 43}, {"question": 20, "votes": 1, "voter": 43}, {"question": 24, "votes": 1, "voter": 43}, {"question": 21, "votes": 1, "voter": 43}, {"question": 31, "votes": 1, "voter": 43}, {"question": 27, "votes": -1, "voter": 43}, {"question": 16, "votes": 1, "voter": 43}, {"question": 11, "votes": 1, "voter": 43}, {"question": 25, "votes": 1, "voter": 43}, {"question": 8, "votes": -1, "voter": 43}, {"question": 2, "votes": 0, "voter": 43}, {"question": 22, "votes": -1, "voter": 43}, {"question": 7, "votes": 1, "voter": 43}, {"question": 1, "votes": -1, "voter": 43}, {"question": 12, "votes": 1, "voter": 43}, {"question": 10, "votes": -1, "voter": 43}, {"question": 14, "votes": 1, "voter": 43}, {"question": 19, "votes": 1, "voter": 43}, {"question": 34, "votes": -1, "voter": 43}, {"question": 36, "votes": 1, "voter": 43}, {"question": 38, "votes": -1, "voter": 43}, {"question": 32, "votes": 1, "voter": 43}, {"question": 9, "votes": -1, "voter": 50}, {"question": 18, "votes": -1, "voter": 50}, {"question": 13, "votes": 1, "voter": 50}, {"question": 39, "votes": 0, "voter": 50}, {"question": 26, "votes": -1, "voter": 50}, {"question": 23, "votes": -1, "voter": 50}, {"question": 33, "votes": -1, "voter": 50}, {"question": 6, "votes": -1, "voter": 50}, {"question": 37, "votes": -1, "voter": 50}, {"question": 5, "votes": 1, "voter": 50}, {"question": 35, "votes": -1, "voter": 50}, {"question": 17, "votes": -1, "voter": 50}, {"question": 3, "votes": -1, "voter": 50}, {"question": 15, "votes": 1, "voter": 50}, {"question": 20, "votes": 1, "voter": 50}, {"question": 24, "votes": -1, "voter": 50}, {"question": 21, "votes": -1, "voter": 50}, {"question": 31, "votes": 1, "voter": 50}, {"question": 27, "votes": -1, "voter": 50}, {"question": 16, "votes": -1, "voter": 50}, {"question": 11, "votes": 1, "voter": 50}, {"question": 25, "votes": 1, "voter": 50}, {"question": 8, "votes": 1, "voter": 50}, {"question": 2, "votes": -1, "voter": 50}, {"question": 22, "votes": 1, "voter": 50}, {"question": 7, "votes": 1, "voter": 50}, {"question": 1, "votes": -1, "voter": 50}, {"question": 12, "votes": 1, "voter": 50}, {"question": 10, "votes": -1, "voter": 50}, {"question": 14, "votes": 1, "voter": 50}, {"question": 19, "votes": 1, "voter": 50}, {"question": 34, "votes": -1, "voter": 50}, {"question": 36, "votes": 1, "voter": 50}, {"question": 38, "votes": 1, "voter": 50}, {"question": 32, "votes": 1, "voter": 50}, {"question": 9, "votes": -1, "voter": 52}, {"question": 18, "votes": -1, "voter": 52}, {"question": 13, "votes": 1, "voter": 52}, {"question": 39, "votes": -1, "voter": 52}, {"question": 26, "votes": -1, "voter": 52}, {"question": 23, "votes": -1, "voter": 52}, {"question": 33, "votes": -1, "voter": 52}, {"question": 6, "votes": -1, "voter": 52}, {"question": 37, "votes": -1, "voter": 52}, {"question": 5, "votes": 1, "voter": 52}, {"question": 35, "votes": 1, "voter": 52}, {"question": 17, "votes": 1, "voter": 52}, {"question": 3, "votes": 1, "voter": 52}, {"question": 15, "votes": 1, "voter": 52}, {"question": 20, "votes": 1, "voter": 52}, {"question": 24, "votes": -1, "voter": 52}, {"question": 21, "votes": -1, "voter": 52}, {"question": 31, "votes": 1, "voter": 52}, {"question": 27, "votes": -1, "voter": 52}, {"question": 16, "votes": 0, "voter": 52}, {"question": 11, "votes": 1, "voter": 52}, {"question": 25, "votes": 1, "voter": 52}, {"question": 8, "votes": 1, "voter": 52}, {"question": 2, "votes": 1, "voter": 52}, {"question": 22, "votes": -1, "voter": 52}, {"question": 7, "votes": 1, "voter": 52}, {"question": 1, "votes": -1, "voter": 52}, {"question": 12, "votes": 1, "voter": 52}, {"question": 10, "votes": -1, "voter": 52}, {"question": 14, "votes": 1, "voter": 52}, {"question": 19, "votes": 1, "voter": 52}, {"question": 34, "votes": 1, "voter": 52}, {"question": 36, "votes": 1, "voter": 52}, {"question": 38, "votes": -1, "voter": 52}, {"question": 32, "votes": 1, "voter": 52}, {"question": 9, "votes": -1, "voter": 53}, {"question": 18, "votes": 0, "voter": 53}, {"question": 13, "votes": 1, "voter": 53}, {"question": 39, "votes": 0, "voter": 53}, {"question": 26, "votes": 1, "voter": 53}, {"question": 23, "votes": -1, "voter": 53}, {"question": 33, "votes": -1, "voter": 53}, {"question": 6, "votes": -1, "voter": 53}, {"question": 37, "votes": -1, "voter": 53}, {"question": 5, "votes": -1, "voter": 53}, {"question": 35, "votes": -1, "voter": 53}, {"question": 17, "votes": 1, "voter": 53}, {"question": 3, "votes": 1, "voter": 53}, {"question": 15, "votes": 1, "voter": 53}, {"question": 20, "votes": 0, "voter": 53}, {"question": 24, "votes": -1, "voter": 53}, {"question": 21, "votes": 1, "voter": 53}, {"question": 31, "votes": 1, "voter": 53}, {"question": 27, "votes": -1, "voter": 53}, {"question": 16, "votes": 1, "voter": 53}, {"question": 11, "votes": 1, "voter": 53}, {"question": 25, "votes": 1, "voter": 53}, {"question": 8, "votes": 0, "voter": 53}, {"question": 2, "votes": 1, "voter": 53}, {"question": 22, "votes": 1, "voter": 53}, {"question": 7, "votes": 1, "voter": 53}, {"question": 1, "votes": -1, "voter": 53}, {"question": 12, "votes": 1, "voter": 53}, {"question": 10, "votes": -1, "voter": 53}, {"question": 14, "votes": 1, "voter": 53}, {"question": 19, "votes": 1, "voter": 53}, {"question": 34, "votes": 1, "voter": 53}, {"question": 36, "votes": 1, "voter": 53}, {"question": 38, "votes": -1, "voter": 53}, {"question": 32, "votes": 1, "voter": 53}, {"question": 9, "votes": -1, "voter": 45}, {"question": 18, "votes": 1, "voter": 45}, {"question": 13, "votes": 1, "voter": 45}, {"question": 39, "votes": -1, "voter": 45}, {"question": 26, "votes": 1, "voter": 45}, {"question": 23, "votes": -1, "voter": 45}, {"question": 33, "votes": -1, "voter": 45}, {"question": 6, "votes": -1, "voter": 45}, {"question": 37, "votes": -1, "voter": 45}, {"question": 5, "votes": 1, "voter": 45}, {"question": 35, "votes": -1, "voter": 45}, {"question": 17, "votes": 1, "voter": 45}, {"question": 3, "votes": 1, "voter": 45}, {"question": 15, "votes": 1, "voter": 45}, {"question": 20, "votes": 1, "voter": 45}, {"question": 24, "votes": 1, "voter": 45}, {"question": 21, "votes": -1, "voter": 45}, {"question": 31, "votes": -1, "voter": 45}, {"question": 27, "votes": -1, "voter": 45}, {"question": 16, "votes": 1, "voter": 45}, {"question": 11, "votes": 1, "voter": 45}, {"question": 25, "votes": 1, "voter": 45}, {"question": 8, "votes": 1, "voter": 45}, {"question": 2, "votes": 1, "voter": 45}, {"question": 22, "votes": 1, "voter": 45}, {"question": 7, "votes": -1, "voter": 45}, {"question": 1, "votes": -1, "voter": 45}, {"question": 12, "votes": 1, "voter": 45}, {"question": 10, "votes": 1, "voter": 45}, {"question": 14, "votes": 1, "voter": 45}, {"question": 19, "votes": 1, "voter": 45}, {"question": 34, "votes": 1, "voter": 45}, {"question": 36, "votes": 1, "voter": 45}, {"question": 38, "votes": 1, "voter": 45}, {"question": 32, "votes": 1, "voter": 45}, {"question": 9, "votes": -1, "voter": 54}, {"question": 18, "votes": 1, "voter": 54}, {"question": 13, "votes": 1, "voter": 54}, {"question": 39, "votes": -1, "voter": 54}, {"question": 26, "votes": 1, "voter": 54}, {"question": 23, "votes": -1, "voter": 54}, {"question": 33, "votes": -1, "voter": 54}, {"question": 6, "votes": -1, "voter": 54}, {"question": 37, "votes": -1, "voter": 54}, {"question": 5, "votes": 1, "voter": 54}, {"question": 35, "votes": -1, "voter": 54}, {"question": 17, "votes": 1, "voter": 54}, {"question": 3, "votes": -1, "voter": 54}, {"question": 15, "votes": 1, "voter": 54}, {"question": 20, "votes": 1, "voter": 54}, {"question": 24, "votes": 1, "voter": 54}, {"question": 21, "votes": -1, "voter": 54}, {"question": 31, "votes": 1, "voter": 54}, {"question": 27, "votes": -1, "voter": 54}, {"question": 16, "votes": 1, "voter": 54}, {"question": 11, "votes": -1, "voter": 54}, {"question": 25, "votes": 1, "voter": 54}, {"question": 8, "votes": 0, "voter": 54}, {"question": 2, "votes": 1, "voter": 54}, {"question": 22, "votes": 1, "voter": 54}, {"question": 7, "votes": 1, "voter": 54}, {"question": 1, "votes": -1, "voter": 54}, {"question": 12, "votes": 0, "voter": 54}, {"question": 10, "votes": -1, "voter": 54}, {"question": 14, "votes": 1, "voter": 54}, {"question": 19, "votes": 1, "voter": 54}, {"question": 34, "votes": 1, "voter": 54}, {"question": 36, "votes": -1, "voter": 54}, {"question": 38, "votes": 1, "voter": 54}, {"question": 32, "votes": 1, "voter": 54}, {"question": 9, "votes": -1, "voter": 55}, {"question": 18, "votes": 1, "voter": 55}, {"question": 13, "votes": 1, "voter": 55}, {"question": 39, "votes": -1, "voter": 55}, {"question": 26, "votes": 1, "voter": 55}, {"question": 23, "votes": -1, "voter": 55}, {"question": 33, "votes": -1, "voter": 55}, {"question": 6, "votes": 1, "voter": 55}, {"question": 37, "votes": -1, "voter": 55}, {"question": 5, "votes": -1, "voter": 55}, {"question": 35, "votes": 1, "voter": 55}, {"question": 17, "votes": 1, "voter": 55}, {"question": 3, "votes": 1, "voter": 55}, {"question": 15, "votes": 1, "voter": 55}, {"question": 20, "votes": -1, "voter": 55}, {"question": 24, "votes": 0, "voter": 55}, {"question": 21, "votes": 1, "voter": 55}, {"question": 31, "votes": 1, "voter": 55}, {"question": 27, "votes": -1, "voter": 55}, {"question": 16, "votes": 1, "voter": 55}, {"question": 11, "votes": 1, "voter": 55}, {"question": 25, "votes": 1, "voter": 55}, {"question": 8, "votes": 1, "voter": 55}, {"question": 2, "votes": 1, "voter": 55}, {"question": 22, "votes": 1, "voter": 55}, {"question": 7, "votes": 1, "voter": 55}, {"question": 1, "votes": -1, "voter": 55}, {"question": 12, "votes": 1, "voter": 55}, {"question": 10, "votes": -1, "voter": 55}, {"question": 14, "votes": 1, "voter": 55}, {"question": 19, "votes": 1, "voter": 55}, {"question": 34, "votes": 0, "voter": 55}, {"question": 36, "votes": 1, "voter": 55}, {"question": 38, "votes": -1, "voter": 55}, {"question": 32, "votes": -1, "voter": 55}, {"question": 9, "votes": 1, "voter": 56}, {"question": 18, "votes": -1, "voter": 56}, {"question": 13, "votes": -1, "voter": 56}, {"question": 39, "votes": 0, "voter": 56}, {"question": 26, "votes": 1, "voter": 56}, {"question": 23, "votes": -1, "voter": 56}, {"question": 33, "votes": -1, "voter": 56}, {"question": 6, "votes": 1, "voter": 56}, {"question": 37, "votes": -1, "voter": 56}, {"question": 5, "votes": 1, "voter": 56}, {"question": 35, "votes": -1, "voter": 56}, {"question": 17, "votes": 1, "voter": 56}, {"question": 3, "votes": -1, "voter": 56}, {"question": 15, "votes": 1, "voter": 56}, {"question": 20, "votes": 0, "voter": 56}, {"question": 24, "votes": 0, "voter": 56}, {"question": 21, "votes": -1, "voter": 56}, {"question": 31, "votes": 1, "voter": 56}, {"question": 27, "votes": 0, "voter": 56}, {"question": 16, "votes": -1, "voter": 56}, {"question": 11, "votes": 0, "voter": 56}, {"question": 25, "votes": 1, "voter": 56}, {"question": 8, "votes": -1, "voter": 56}, {"question": 2, "votes": 1, "voter": 56}, {"question": 22, "votes": -1, "voter": 56}, {"question": 7, "votes": 1, "voter": 56}, {"question": 1, "votes": -1, "voter": 56}, {"question": 12, "votes": 1, "voter": 56}, {"question": 10, "votes": 0, "voter": 56}, {"question": 14, "votes": 1, "voter": 56}, {"question": 19, "votes": 1, "voter": 56}, {"question": 34, "votes": 1, "voter": 56}, {"question": 36, "votes": 0, "voter": 56}, {"question": 38, "votes": -1, "voter": 56}, {"question": 32, "votes": -1, "voter": 56}, {"question": 9, "votes": 0, "voter": 58}, {"question": 18, "votes": -1, "voter": 58}, {"question": 13, "votes": 1, "voter": 58}, {"question": 39, "votes": -1, "voter": 58}, {"question": 26, "votes": 1, "voter": 58}, {"question": 23, "votes": 0, "voter": 58}, {"question": 33, "votes": -1, "voter": 58}, {"question": 6, "votes": 0, "voter": 58}, {"question": 37, "votes": -1, "voter": 58}, {"question": 5, "votes": 0, "voter": 58}, {"question": 35, "votes": -1, "voter": 58}, {"question": 17, "votes": 1, "voter": 58}, {"question": 3, "votes": 1, "voter": 58}, {"question": 15, "votes": 1, "voter": 58}, {"question": 20, "votes": -1, "voter": 58}, {"question": 24, "votes": 0, "voter": 58}, {"question": 21, "votes": 0, "voter": 58}, {"question": 31, "votes": 1, "voter": 58}, {"question": 27, "votes": 0, "voter": 58}, {"question": 16, "votes": 1, "voter": 58}, {"question": 11, "votes": 1, "voter": 58}, {"question": 25, "votes": 1, "voter": 58}, {"question": 8, "votes": -1, "voter": 58}, {"question": 2, "votes": 1, "voter": 58}, {"question": 22, "votes": 0, "voter": 58}, {"question": 7, "votes": 1, "voter": 58}, {"question": 1, "votes": -1, "voter": 58}, {"question": 12, "votes": 1, "voter": 58}, {"question": 10, "votes": -1, "voter": 58}, {"question": 14, "votes": 1, "voter": 58}, {"question": 19, "votes": 1, "voter": 58}, {"question": 34, "votes": 1, "voter": 58}, {"question": 36, "votes": 1, "voter": 58}, {"question": 38, "votes": 1, "voter": 58}, {"question": 32, "votes": 1, "voter": 58}]