[{"short_name": "\u010cSSD", "name": "\u010cesk\u00e1 strana soci\u00e1ln\u011b demokratick\u00e1", "friendly_name": "cssd", "id": "2"}, {"short_name": "KDU-\u010cSL", "name": "KDU-\u010cSL a nez\u00e1visl\u00ed", "friendly_name": "kdu-csl", "id": "6"}, {"short_name": "ODS", "name": "Ob\u010dansk\u00e1 demokratick\u00e1 strana", "friendly_name": "ods", "id": "12"}, {"short_name": "PSZ", "name": "Pro sport a zdrav\u00ed", "friendly_name": "psz", "id": "15"}, {"short_name": "SLK", "name": "Starostov\u00e9 pro Libereck\u00fd kraj", "friendly_name": "slk", "id": "3"}, {"short_name": "SPOZ", "name": "SPOZ", "friendly_name": "spoz", "id": "14"}, {"short_name": "TOP 09", "name": "TOP 09", "friendly_name": "top-09", "id": "8"}]