{"124875": {"country_code": "dk", "political_group": "European Conservatives and Reformists Group", "party_logo": "image/logo/dansk-folkeparti.jpg", "country": "Denmark", "id": "124875", "votes": {"11": 1, "6": 1, "3": 1, "12": 0, "2": -1, "15": 1, "13": 0, "16": -1, "14": -1, "4": 0, "10": 1, "5": 0, "8": 0, "1": -1, "7": -1, "9": 1, "17": 1}, "name": "Anders Primdahl VISTISEN", "party": "Dansk Folkeparti", "political_group_logo": "http://www.europarl.europa.eu/ep_framework/img/group/group_icon_ecr.gif", "picture": "http://www.europarl.europa.eu/mepphoto/124875.jpg", "country_logo": "http://www.europarl.europa.eu/ep_framework/img/flag/flag_icon_dk.gif"}, "124876": {"country_code": "dk", "political_group": "European Conservatives and Reformists Group", "party_logo": "image/logo/dansk-folkeparti.jpg", "country": "Denmark", "id": "124876", "votes": {"11": 1, "6": 1, "3": 1, "12": 0, "2": 0, "15": 1, "13": 0, "16": -1, "14": 0, "4": 0, "10": 0, "5": 0, "8": 0, "1": 0, "7": -1, "9": 1, "17": 1}, "name": "Rikke KARLSSON", "party": "Dansk Folkeparti", "political_group_logo": "http://www.europarl.europa.eu/ep_framework/img/group/group_icon_ecr.gif", "picture": "http://www.europarl.europa.eu/mepphoto/124876.jpg", "country_logo": "http://www.europarl.europa.eu/ep_framework/img/flag/flag_icon_dk.gif"}, "124872": {"country_code": "dk", "political_group": "Group of the Alliance of Liberals and Democrats for Europe", "party_logo": "image/logo/det-radikale-venstre.jpg", "country": "Denmark", "id": "124872", "votes": {"11": 1, "6": 1, "3": 0, "12": 1, "2": 1, "15": 0, "13": -1, "16": 1, "14": 1, "4": 1, "10": 1, "5": 1, "8": 1, "1": 1, "7": 0, "9": -1, "17": 0}, "name": "Morten Helveg PETERSEN", "party": "Det Radikale Venstre", "political_group_logo": "http://www.europarl.europa.eu/ep_framework/img/group/group_icon_aldeadle.gif", "picture": "http://www.europarl.europa.eu/mepphoto/124872.jpg", "country_logo": "http://www.europarl.europa.eu/ep_framework/img/flag/flag_icon_dk.gif"}, "124870": {"country_code": "dk", "political_group": "Group of the Progressive Alliance of Socialists and Democrats in the European Parliament", "party_logo": "image/logo/socialdemokratiet.jpg", "country": "Denmark", "id": "124870", "votes": {"11": 1, "6": 1, "3": 1, "12": 1, "2": 1, "15": 0, "13": -1, "16": 1, "14": -1, "4": 1, "10": 1, "5": 1, "8": 1, "1": 0, "7": 1, "9": 1, "17": 1}, "name": "Jeppe KOFOD", "party": "Socialdemokratiet", "political_group_logo": "http://www.europarl.europa.eu/ep_framework/img/group/group_icon_sd.gif", "picture": "http://www.europarl.europa.eu/mepphoto/124870.jpg", "country_logo": "http://www.europarl.europa.eu/ep_framework/img/flag/flag_icon_dk.gif"}, "96705": {"country_code": "dk", "political_group": "Group of the European People's Party (Christian Democrats)", "party_logo": "image/logo/det-konservative-folkeparti.jpg", "country": "Denmark", "id": "96705", "votes": {"11": 1, "6": 0, "3": -1, "12": 1, "2": 1, "15": 1, "13": -1, "16": 0, "14": 0, "4": 1, "10": 1, "5": 1, "8": 1, "1": 0, "7": -1, "9": 1, "17": 1}, "name": "Bendt BENDTSEN", "party": "Det Konservative Folkeparti", "political_group_logo": "http://www.europarl.europa.eu/ep_framework/img/group/group_icon_epp.gif", "picture": "http://www.europarl.europa.eu/mepphoto/96705.jpg", "country_logo": "http://www.europarl.europa.eu/ep_framework/img/flag/flag_icon_dk.gif"}, "96663": {"country_code": "dk", "political_group": "European Conservatives and Reformists Group", "party_logo": "image/logo/dansk-folkeparti.jpg", "country": "Denmark", "id": "96663", "votes": {"11": 1, "6": 1, "3": 1, "12": 0, "2": -1, "15": 1, "13": 0, "16": -1, "14": -1, "4": 0, "10": 0, "5": 0, "8": 0, "1": -1, "7": -1, "9": 1, "17": 1}, "name": "Morten MESSERSCHMIDT", "party": "Dansk Folkeparti", "political_group_logo": "http://www.europarl.europa.eu/ep_framework/img/group/group_icon_ecr.gif", "picture": "http://www.europarl.europa.eu/mepphoto/96663.jpg", "country_logo": "http://www.europarl.europa.eu/ep_framework/img/flag/flag_icon_dk.gif"}, "122885": {"country_code": "dk", "political_group": "Confederal Group of the European United Left - Nordic Green Left", "party_logo": "image/logo/folkebevaegelsen-mod-eu.jpg", "country": "Denmark", "id": "122885", "votes": {"11": 0, "6": -1, "3": 1, "12": -1, "2": -1, "15": -1, "13": 1, "16": 1, "14": -1, "4": -1, "10": -1, "5": -1, "8": 0, "1": 0, "7": 1, "9": 0, "17": 1}, "name": "Rina Ronja KARI", "party": "Folkebev\u00e6gelsen mod EU", "political_group_logo": "http://www.europarl.europa.eu/ep_framework/img/group/group_icon_guengl.gif", "picture": "http://www.europarl.europa.eu/mepphoto/122885.jpg", "country_logo": "http://www.europarl.europa.eu/ep_framework/img/flag/flag_icon_dk.gif"}, "28161": {"country_code": "dk", "political_group": "Group of the Greens/European Free Alliance", "party_logo": "image/logo/socialistisk-folkeparti.jpg", "country": "Denmark", "id": "28161", "votes": {"11": 1, "6": -1, "3": 1, "12": 1, "2": 1, "15": -1, "13": -1, "16": 1, "14": 1, "4": -1, "10": 1, "5": 0, "8": 1, "1": 1, "7": 1, "9": -1, "17": 1}, "name": "Margrete AUKEN", "party": "Socialistisk Folkeparti", "political_group_logo": "http://www.europarl.europa.eu/ep_framework/img/group/group_icon_greensefa.gif", "picture": "http://www.europarl.europa.eu/mepphoto/28161.jpg", "country_logo": "http://www.europarl.europa.eu/ep_framework/img/flag/flag_icon_dk.gif"}, "124880": {"country_code": "dk", "political_group": "Group of the Alliance of Liberals and Democrats for Europe", "party_logo": "image/logo/venstre-danmarks-liberale-parti.jpg", "country": "Denmark", "id": "124880", "votes": {"11": 1, "6": 0, "3": -1, "12": 0, "2": 0, "15": 1, "13": -1, "16": -1, "14": 1, "4": 1, "10": 1, "5": 1, "8": 1, "1": 0, "7": 0, "9": -1, "17": 1}, "name": "Ulla T\u00d8RN\u00c6S", "party": "Venstre, Danmarks Liberale Parti", "political_group_logo": "http://www.europarl.europa.eu/ep_framework/img/group/group_icon_aldeadle.gif", "picture": "http://www.europarl.europa.eu/mepphoto/124880.jpg", "country_logo": "http://www.europarl.europa.eu/ep_framework/img/flag/flag_icon_dk.gif"}, "96710": {"country_code": "dk", "political_group": "Group of the Alliance of Liberals and Democrats for Europe", "party_logo": "image/logo/venstre-danmarks-liberale-parti.jpg", "country": "Denmark", "id": "96710", "votes": {"11": 1, "6": 1, "3": -1, "12": 0, "2": 0, "15": 1, "13": 0, "16": -1, "14": 1, "4": 1, "10": 0, "5": 1, "8": 1, "1": 0, "7": 0, "9": 0, "17": 1}, "name": "Jens ROHDE", "party": "Venstre, Danmarks Liberale Parti", "political_group_logo": "http://www.europarl.europa.eu/ep_framework/img/group/group_icon_aldeadle.gif", "picture": "http://www.europarl.europa.eu/mepphoto/96710.jpg", "country_logo": "http://www.europarl.europa.eu/ep_framework/img/flag/flag_icon_dk.gif"}, "28154": {"country_code": "dk", "political_group": "Group of the Progressive Alliance of Socialists and Democrats in the European Parliament", "party_logo": "image/logo/socialdemokratiet.jpg", "country": "Denmark", "id": "28154", "votes": {"11": 1, "6": 1, "3": -1, "12": 1, "2": 1, "15": 1, "13": -1, "16": 1, "14": -1, "4": 0, "10": 1, "5": 0, "8": 1, "1": 0, "7": 1, "9": 1, "17": 1}, "name": "Ole CHRISTENSEN", "party": "Socialdemokratiet", "political_group_logo": "http://www.europarl.europa.eu/ep_framework/img/group/group_icon_sd.gif", "picture": "http://www.europarl.europa.eu/mepphoto/28154.jpg", "country_logo": "http://www.europarl.europa.eu/ep_framework/img/flag/flag_icon_dk.gif"}, "124878": {"country_code": "dk", "political_group": "European Conservatives and Reformists Group", "party_logo": "image/logo/dansk-folkeparti.jpg", "country": "Denmark", "id": "124878", "votes": {"11": 1, "6": 1, "3": 1, "12": 0, "2": -1, "15": 1, "13": 0, "16": -1, "14": -1, "4": 0, "10": 1, "5": 0, "8": 0, "1": -1, "7": -1, "9": 1, "17": 1}, "name": "J\u00f8rn DOHRMANN", "party": "Dansk Folkeparti", "political_group_logo": "http://www.europarl.europa.eu/ep_framework/img/group/group_icon_ecr.gif", "picture": "http://www.europarl.europa.eu/mepphoto/124878.jpg", "country_logo": "http://www.europarl.europa.eu/ep_framework/img/flag/flag_icon_dk.gif"}, "37312": {"country_code": "dk", "political_group": "Group of the Progressive Alliance of Socialists and Democrats in the European Parliament", "party_logo": "image/logo/socialdemokratiet.jpg", "country": "Denmark", "id": "37312", "votes": {"11": 1, "6": 1, "3": 1, "12": 1, "2": 0, "15": 1, "13": -1, "16": 1, "14": -1, "4": 1, "10": 1, "5": 1, "8": 1, "1": 0, "7": 1, "9": 1, "17": 1}, "name": "Christel SCHALDEMOSE", "party": "Socialdemokratiet", "political_group_logo": "http://www.europarl.europa.eu/ep_framework/img/group/group_icon_sd.gif", "picture": "http://www.europarl.europa.eu/mepphoto/37312.jpg", "country_logo": "http://www.europarl.europa.eu/ep_framework/img/flag/flag_icon_dk.gif"}}